device_cloud/__init__.py
device_cloud/app_relay.py
device_cloud/bk.relay.py
device_cloud/identity.py
device_cloud/old.relay.py
device_cloud/osal.py
device_cloud/ota_handler.py
device_cloud/relay.py
device_cloud/rest.py
device_cloud/_core/__init__.py
device_cloud/_core/client.py
device_cloud/_core/constants.py
device_cloud/_core/defs.py
device_cloud/_core/handler.py
device_cloud/_core/tr50.py
device_cloud/test/__init__.py
device_cloud/test/test_cases.py
device_cloud/test/test_helpers.py
device_cloud-18.6.19.data/data/share/device_cloud/COPYING.txt
device_cloud-18.6.19.data/data/share/device_cloud/README.macOSX.md
device_cloud-18.6.19.data/data/share/device_cloud/README.md
device_cloud-18.6.19.data/data/share/device_cloud/README.style.md
device_cloud-18.6.19.data/data/share/device_cloud/device_manager.py
device_cloud-18.6.19.data/data/share/device_cloud/generate_config.py
device_cloud-18.6.19.data/data/share/device_cloud/iot.cfg
device_cloud-18.6.19.data/data/share/device_cloud/validate_app.py
device_cloud-18.6.19.data/data/share/device_cloud/validate_device_manager.py
device_cloud-18.6.19.data/data/share/device_cloud/validate_script.py
device_cloud-18.6.19.data/data/share/device_cloud/demo/action.bat
device_cloud-18.6.19.data/data/share/device_cloud/demo/action.sh
device_cloud-18.6.19.data/data/share/device_cloud/demo/iot-simple-actions.py
device_cloud-18.6.19.data/data/share/device_cloud/demo/iot-simple-location.py
device_cloud-18.6.19.data/data/share/device_cloud/demo/iot-simple-telemetry.py
device_cloud-18.6.19.data/data/share/device_cloud/docs/paho-mqtt-QOS.md
device_cloud-18.6.19.data/data/share/device_cloud/share/PUBLISHING.md
device_cloud-18.6.19.data/data/share/device_cloud/share/cloud-test.py.in
device_cloud-18.6.19.data/data/share/device_cloud/share/device-cloud-watchdog-test.sh.in
device_cloud-18.6.19.data/data/share/device_cloud/share/device-cloud-watchdog.conf.in
device_cloud-18.6.19.dist-info/DESCRIPTION.rst
device_cloud-18.6.19.dist-info/METADATA
device_cloud-18.6.19.dist-info/RECORD
device_cloud-18.6.19.dist-info/WHEEL
device_cloud-18.6.19.dist-info/metadata.json
device_cloud-18.6.19.dist-info/top_level.txt
