Metadata-Version: 2.0
Name: device-cloud
Version: 18.6.19
Summary: Python library for Wind River's Helix Device Cloud
Home-page: http://www.windriver.com/products/helix/
Author: Wind River Systems
Author-email: 
Maintainer: Paul Barrette
Maintainer-email: paul.barrette@windriver.com
License: Apache License, Version 2.0
Platform: UNKNOWN
Classifier: Development Status :: 5 - Production/Stable
Classifier: Intended Audience :: Developers
Classifier: Natural Language :: English
Classifier: Programming Language :: Python :: 2.7
Classifier: Programming Language :: Python :: 3.4
Classifier: Operating System :: Microsoft :: Windows :: Windows 7
Classifier: Operating System :: Microsoft :: Windows :: Windows 10
Classifier: Operating System :: POSIX :: Linux
Classifier: Topic :: Software Development :: Libraries :: Python Modules
Requires-Dist: PySocks (==1.6.8)
Requires-Dist: certifi (==2017.11.5)
Requires-Dist: paho-mqtt (==1.3.1)
Requires-Dist: queues (==0.6.3)
Requires-Dist: requests (==2.18.4)
Requires-Dist: simplejson (==3.8.1)
Requires-Dist: urllib3 (==1.22)
Requires-Dist: websocket-client (==0.47.0)
